pythonic_fp/credits/__init__.py
pythonic_fp/credits/py.typed
pythonic_fp_credits-1.3.1.dist-info/licenses/LICENSE
pythonic_fp_credits-1.3.1.dist-info/WHEEL
pythonic_fp_credits-1.3.1.dist-info/METADATA
pythonic_fp_credits-1.3.1.dist-info/RECORD
